lnbits_lib/__init__.py
lnbits_lib/db.py
lnbits_lib/settings.py
lnbits_lib-0.0.1.dist-info/METADATA
lnbits_lib-0.0.1.dist-info/WHEEL
lnbits_lib-0.0.1.dist-info/RECORD
